LICENSE
MANIFEST.in
README.rst
setup.py
psydac/__init__.py
psydac/version.py
psydac.egg-info/PKG-INFO
psydac.egg-info/SOURCES.txt
psydac.egg-info/dependency_links.txt
psydac.egg-info/entry_points.txt
psydac.egg-info/requires.txt
psydac.egg-info/top_level.txt
psydac.egg-info/zip-safe
psydac/api/__init__.py
psydac/api/basic.py
psydac/api/discretization.py
psydac/api/essential_bc.py
psydac/api/expr.py
psydac/api/fem.py
psydac/api/glt.py
psydac/api/grid.py
psydac/api/postprocessing.py
psydac/api/settings.py
psydac/api/ast/__init__.py
psydac/api/ast/basic.py
psydac/api/ast/evaluation.py
psydac/api/ast/expr.py
psydac/api/ast/fem.py
psydac/api/ast/glt.py
psydac/api/ast/utilities.py
psydac/api/printing/__init__.py
psydac/api/printing/pycode.py
psydac/api/tests/__init__.py
psydac/api/tests/test_api_1d_compatible_spaces.py
psydac/api/tests/test_api_2d_compatible_spaces.py
psydac/api/tests/test_api_2d_scalar.py
psydac/api/tests/test_api_2d_scalar_mapping.py
psydac/api/tests/test_api_2d_system.py
psydac/api/tests/test_api_2d_vector.py
psydac/api/tests/test_api_2d_vector_mapping.py
psydac/api/tests/test_api_3d_scalar.py
psydac/api/tests/test_api_3d_scalar_mapping.py
psydac/api/tests/test_api_3d_vector.py
psydac/api/tests/test_api_3d_vector_mapping.py
psydac/api/tests/test_api_expr_2d_scalar.py
psydac/api/tests/test_api_feec_2d.py
psydac/api/tests/test_api_glt_2d_scalar.py
psydac/api/tests/test_api_glt_2d_scalar_mapping.py
psydac/api/tests/test_api_glt_2d_vector.py
psydac/api/tests/utils.py
psydac/cad/__init__.py
psydac/cad/cad.py
psydac/cad/gallery.py
psydac/cad/geometry.py
psydac/cad/utils.py
psydac/cad/tests/test_geometry.py
psydac/cad/tests/data/square_1_elem.h5
psydac/cad/tests/data/square_8_elem.h5
psydac/cmd/__init__.py
psydac/cmd/mesh.py
psydac/core/__init__.py
psydac/core/bsp-f2pywrappers2.f90
psydac/core/bsp.F90
psydac/core/bsp.pyf
psydac/core/bsp_ext.F90
psydac/core/bsplines.py
psydac/core/interface.py
psydac/core/external/bspline.F90
psydac/core/external/bsplpp.F90
psydac/core/external/bsplvb.F90
psydac/core/external/interv.F90
psydac/core/external/pppack.F90
psydac/core/external/ppvalu.F90
psydac/core/tests/__init__.py
psydac/core/tests/test_bsplines.py
