Metadata-Version: 2.1
Name: psydac
Version: 0.1
Summary: Python package for BSplines/NURBS
Home-page: http://www.ahmed.ratnani.org
Author: Ahmed Ratnani, Jalal Lakhlili, Yaman Güçlü
Author-email: ratnaniahmed@gmail.com
License: LICENSE.txt
Keywords: FEM,IGA,BSplines
Platform: UNKNOWN
License-File: LICENSE
